.gitignore
LICENSE
README.md
mypy.ini
pyproject.toml
setup.py
tox.ini
.circleci/config.yml
django_girders/__init__.py
django_girders/models.py
django_girders.egg-info/PKG-INFO
django_girders.egg-info/SOURCES.txt
django_girders.egg-info/dependency_links.txt
django_girders.egg-info/requires.txt
django_girders.egg-info/top_level.txt
django_girders/configuration/__init__.py
django_girders/configuration/_base.py
django_girders/configuration/_celery.py
django_girders/configuration/_configuration.py
django_girders/configuration/_cors.py
django_girders/configuration/_database.py
django_girders/configuration/_debug.py
django_girders/configuration/_django.py
django_girders/configuration/_email.py
django_girders/configuration/_extensions.py
django_girders/configuration/_filter.py
django_girders/configuration/_logging.py
django_girders/configuration/_rest_framework.py
django_girders/configuration/_static.py
django_girders/configuration/_storage.py