Metadata-Version: 2.1
Name: django-girders
Version: 0.0.11
Summary: Django utilities for data management applications
Home-page: https://github.com/brianhelba/django-girders
Author: Kitware, Inc
Author-email: kitware@kitware.com
License: Apache 2.0
Project-URL: Bug Reports, https://github.com/brianhelba/django-girders/issues
Project-URL: Source, https://github.com/brianhelba/django-girders
Keywords: django girder girders
Platform: UNKNOWN
Classifier: Development Status :: 3 - Alpha
Classifier: Environment :: Web Environment
Classifier: Framework :: Django :: 3.0
Classifier: Framework :: Django
Classifier: Intended Audience :: Developers
Classifier: License :: OSI Approved :: Apache Software License
Classifier: Operating System :: OS Independent
Classifier: Programming Language :: Python :: 3
Classifier: Programming Language :: Python :: 3.8
Classifier: Programming Language :: Python
Requires-Python: >=3.8
